py_nessus_pro/__init__.py
py_nessus_pro/py_nessus_pro.py
py_nessus_pro/py_nessus_pro_cli.py
py_nessus_pro/scan.py
py_nessus_pro-1.3.2.dist-info/licenses/LICENSE
py_nessus_pro-1.3.2.dist-info/METADATA
py_nessus_pro-1.3.2.dist-info/WHEEL
py_nessus_pro-1.3.2.dist-info/entry_points.txt
py_nessus_pro-1.3.2.dist-info/top_level.txt
py_nessus_pro-1.3.2.dist-info/RECORD
