Metadata-Version: 2.4
Name: py_nessus_pro
Version: 1.3.2
Summary: Python library for managing Nessus Professional.
Home-page: https://github.com/Matbe34/py-nessus-pro
Author: Matbe34
Classifier: Programming Language :: Python :: 3
License-File: LICENSE
Requires-Dist: selenium
Requires-Dist: beautifulsoup4
Requires-Dist: python-slugify
Requires-Dist: requests
Requires-Dist: loguru
Requires-Dist: typer
Requires-Dist: typing
Dynamic: author
Dynamic: classifier
Dynamic: description
Dynamic: home-page
Dynamic: license-file
Dynamic: requires-dist
Dynamic: summary
